Workbook

Sheet 参数与情景
A1: 简化单位经济与现金模板：待填参数，不是已验证预测
A2: 适用前提：每月销量与单价固定，即收即付；税费、融资、赊账、库存与季节性另建模型。
A3: 参数/结果 | B3: 保守 | C3: 基准 | D3: 较好 | E3: 单位/说明 | F3: 依据与验证状态
A4: 月销量 | E4: 单位/月；单位可为订单或服务，按项目定义 | F4: 待填写来源/估算方法；未验证
A5: 单位净收入 | E5: 元/单位；不把交易额当平台收入 | F5: 待填写来源/估算方法；未验证
A6: 单位变动成本 | E6: 元/单位；含对应直接支出 | F6: 待填写来源/估算方法；未验证
A7: 月固定现金支出 | E7: 元/月 | F7: 待填写来源/估算方法；未验证
A8: 一次启动投入 | E8: 元；发生于第0月 | F8: 待填写来源/估算方法；未验证
A9: 初始可用现金 | E9: 元；不含尚未到账融资 | F9: 待填写来源/估算方法；未验证
A10: 安全缓冲 | E10: 元；由业务约束设定 | F10: 待填写来源/估算方法；未验证
A12: 以上每个情景的7项参数都填写后才显示结果；合法的0值可填写0。
A15: 月收入 | B15: =IF(COUNT(B4:B10)<7,"待填",B4*B5) | C15: =IF(COUNT(C4:C10)<7,"待填",C4*C5) | D15: =IF(COUNT(D4:D10)<7,"待填",D4*D5)
A16: 月变动成本 | B16: =IF(COUNT(B4:B10)<7,"待填",B4*B6) | C16: =IF(COUNT(C4:C10)<7,"待填",C4*C6) | D16: =IF(COUNT(D4:D10)<7,"待填",D4*D6)
A17: 月贡献 | B17: =IF(COUNT(B4:B10)<7,"待填",B15-B16) | C17: =IF(COUNT(C4:C10)<7,"待填",C15-C16) | D17: =IF(COUNT(D4:D10)<7,"待填",D15-D16)
A18: 月经营净流入（即收即付） | B18: =IF(COUNT(B4:B10)<7,"待填",B17-B7) | C18: =IF(COUNT(C4:C10)<7,"待填",C17-C7) | D18: =IF(COUNT(D4:D10)<7,"待填",D17-D7)
A19: 盈亏平衡销量 | B19: =IF(COUNT(B4:B10)<7,"待填",IF(B5<=B6,"单位贡献不为正",ROUNDUP(B7/(B5-B6),0))) | C19: =IF(COUNT(C4:C10)<7,"待填",IF(C5<=C6,"单位贡献不为正",ROUNDUP(C7/(C5-C6),0))) | D19: =IF(COUNT(D4:D10)<7,"待填",IF(D5<=D6,"单位贡献不为正",ROUNDUP(D7/(D5-D6),0)))
A20: 12个月最低现金（含启动时点） | B20: =IF(COUNT(B4:B10)<7,"待填",B9-B8+MIN(0,B18)*12) | C20: =IF(COUNT(C4:C10)<7,"待填",C9-C8+MIN(0,C18)*12) | D20: =IF(COUNT(D4:D10)<7,"待填",D9-D8+MIN(0,D18)*12)
A21: 维持安全缓冲的额外资金缺口 | B21: =IF(COUNT(B4:B10)<7,"待填",MAX(0,B10-B20)) | C21: =IF(COUNT(C4:C10)<7,"待填",MAX(0,C10-C20)) | D21: =IF(COUNT(D4:D10)<7,"待填",MAX(0,D10-D20))

Sheet 月度现金
A1: 月份 | B1: 保守期末现金 | C1: 基准期末现金 | D1: 较好期末现金
A2: 0 | B2: =IF(COUNT('参数与情景'!B4:B10)<7,"待填",'参数与情景'!B9-'参数与情景'!B8+'参数与情景'!B18*A2) | C2: =IF(COUNT('参数与情景'!C4:C10)<7,"待填",'参数与情景'!C9-'参数与情景'!C8+'参数与情景'!C18*A2) | D2: =IF(COUNT('参数与情景'!D4:D10)<7,"待填",'参数与情景'!D9-'参数与情景'!D8+'参数与情景'!D18*A2)
A3: 1 | B3: =IF(COUNT('参数与情景'!B4:B10)<7,"待填",'参数与情景'!B9-'参数与情景'!B8+'参数与情景'!B18*A3) | C3: =IF(COUNT('参数与情景'!C4:C10)<7,"待填",'参数与情景'!C9-'参数与情景'!C8+'参数与情景'!C18*A3) | D3: =IF(COUNT('参数与情景'!D4:D10)<7,"待填",'参数与情景'!D9-'参数与情景'!D8+'参数与情景'!D18*A3)
A4: 2 | B4: =IF(COUNT('参数与情景'!B4:B10)<7,"待填",'参数与情景'!B9-'参数与情景'!B8+'参数与情景'!B18*A4) | C4: =IF(COUNT('参数与情景'!C4:C10)<7,"待填",'参数与情景'!C9-'参数与情景'!C8+'参数与情景'!C18*A4) | D4: =IF(COUNT('参数与情景'!D4:D10)<7,"待填",'参数与情景'!D9-'参数与情景'!D8+'参数与情景'!D18*A4)
A5: 3 | B5: =IF(COUNT('参数与情景'!B4:B10)<7,"待填",'参数与情景'!B9-'参数与情景'!B8+'参数与情景'!B18*A5) | C5: =IF(COUNT('参数与情景'!C4:C10)<7,"待填",'参数与情景'!C9-'参数与情景'!C8+'参数与情景'!C18*A5) | D5: =IF(COUNT('参数与情景'!D4:D10)<7,"待填",'参数与情景'!D9-'参数与情景'!D8+'参数与情景'!D18*A5)
A6: 4 | B6: =IF(COUNT('参数与情景'!B4:B10)<7,"待填",'参数与情景'!B9-'参数与情景'!B8+'参数与情景'!B18*A6) | C6: =IF(COUNT('参数与情景'!C4:C10)<7,"待填",'参数与情景'!C9-'参数与情景'!C8+'参数与情景'!C18*A6) | D6: =IF(COUNT('参数与情景'!D4:D10)<7,"待填",'参数与情景'!D9-'参数与情景'!D8+'参数与情景'!D18*A6)
A7: 5 | B7: =IF(COUNT('参数与情景'!B4:B10)<7,"待填",'参数与情景'!B9-'参数与情景'!B8+'参数与情景'!B18*A7) | C7: =IF(COUNT('参数与情景'!C4:C10)<7,"待填",'参数与情景'!C9-'参数与情景'!C8+'参数与情景'!C18*A7) | D7: =IF(COUNT('参数与情景'!D4:D10)<7,"待填",'参数与情景'!D9-'参数与情景'!D8+'参数与情景'!D18*A7)
A8: 6 | B8: =IF(COUNT('参数与情景'!B4:B10)<7,"待填",'参数与情景'!B9-'参数与情景'!B8+'参数与情景'!B18*A8) | C8: =IF(COUNT('参数与情景'!C4:C10)<7,"待填",'参数与情景'!C9-'参数与情景'!C8+'参数与情景'!C18*A8) | D8: =IF(COUNT('参数与情景'!D4:D10)<7,"待填",'参数与情景'!D9-'参数与情景'!D8+'参数与情景'!D18*A8)
A9: 7 | B9: =IF(COUNT('参数与情景'!B4:B10)<7,"待填",'参数与情景'!B9-'参数与情景'!B8+'参数与情景'!B18*A9) | C9: =IF(COUNT('参数与情景'!C4:C10)<7,"待填",'参数与情景'!C9-'参数与情景'!C8+'参数与情景'!C18*A9) | D9: =IF(COUNT('参数与情景'!D4:D10)<7,"待填",'参数与情景'!D9-'参数与情景'!D8+'参数与情景'!D18*A9)
A10: 8 | B10: =IF(COUNT('参数与情景'!B4:B10)<7,"待填",'参数与情景'!B9-'参数与情景'!B8+'参数与情景'!B18*A10) | C10: =IF(COUNT('参数与情景'!C4:C10)<7,"待填",'参数与情景'!C9-'参数与情景'!C8+'参数与情景'!C18*A10) | D10: =IF(COUNT('参数与情景'!D4:D10)<7,"待填",'参数与情景'!D9-'参数与情景'!D8+'参数与情景'!D18*A10)
A11: 9 | B11: =IF(COUNT('参数与情景'!B4:B10)<7,"待填",'参数与情景'!B9-'参数与情景'!B8+'参数与情景'!B18*A11) | C11: =IF(COUNT('参数与情景'!C4:C10)<7,"待填",'参数与情景'!C9-'参数与情景'!C8+'参数与情景'!C18*A11) | D11: =IF(COUNT('参数与情景'!D4:D10)<7,"待填",'参数与情景'!D9-'参数与情景'!D8+'参数与情景'!D18*A11)
A12: 10 | B12: =IF(COUNT('参数与情景'!B4:B10)<7,"待填",'参数与情景'!B9-'参数与情景'!B8+'参数与情景'!B18*A12) | C12: =IF(COUNT('参数与情景'!C4:C10)<7,"待填",'参数与情景'!C9-'参数与情景'!C8+'参数与情景'!C18*A12) | D12: =IF(COUNT('参数与情景'!D4:D10)<7,"待填",'参数与情景'!D9-'参数与情景'!D8+'参数与情景'!D18*A12)
A13: 11 | B13: =IF(COUNT('参数与情景'!B4:B10)<7,"待填",'参数与情景'!B9-'参数与情景'!B8+'参数与情景'!B18*A13) | C13: =IF(COUNT('参数与情景'!C4:C10)<7,"待填",'参数与情景'!C9-'参数与情景'!C8+'参数与情景'!C18*A13) | D13: =IF(COUNT('参数与情景'!D4:D10)<7,"待填",'参数与情景'!D9-'参数与情景'!D8+'参数与情景'!D18*A13)
A14: 12 | B14: =IF(COUNT('参数与情景'!B4:B10)<7,"待填",'参数与情景'!B9-'参数与情景'!B8+'参数与情景'!B18*A14) | C14: =IF(COUNT('参数与情景'!C4:C10)<7,"待填",'参数与情景'!C9-'参数与情景'!C8+'参数与情景'!C18*A14) | D14: =IF(COUNT('参数与情景'!D4:D10)<7,"待填",'参数与情景'!D9-'参数与情景'!D8+'参数与情景'!D18*A14)

Sheet 使用与限制
A1: 这是一份空白模板，未填任何市场数据、价格、用户量或收入预测。
A2: 本表只适用简化单位模型。订阅留存、不同计价周期、平台费率、收付款时点、税费、库存与融资需按项目改造。
A3: 先为各参数补真实来源或明确估算方法，再做情景；三种情景不是已经验证的未来。
A4: 改变参数后在电子表格软件中重新计算；不能以文件能打开代替公式结果验收。
A5: 现金包含第0月投入，单位贡献非正时不虚构正数盈亏平衡销量。
A6: 初始可用现金只记录已可用金额；资金缺口不代表一定能融资或承诺投资回报。
